BackupMega-0.0.1.dist-info/METADATA
BackupMega-0.0.1.dist-info/RECORD
BackupMega-0.0.1.dist-info/WHEEL
BackupMega-0.0.1.dist-info/entry_points.txt
BackupMega-0.0.1.dist-info/top_level.txt
backup/__init__.py
backup/build_files.py
backup/main.py
