Metadata-Version: 2.1
Name: BackupMega
Version: 0.0.1
Summary: Backup system and push backup zip to storage mega.nz.
Home-page: https://github.com/ProgMeli/backup-mega
Author: Nurlan Melis (NMelis)
Author-email: melis.zhoroev@gmail.com
License: LICENSE.txt
Platform: UNKNOWN
